benchmarks/propositional/models/Baseline/Random-Model/random_model.py
benchmarks/relational/models/Baseline/Random-Model/random_model.py
benchmarks/relational/models/Baseline/Transitive-Closure/transitive_closure.py
benchmarks/syllogistic/models/2012-Khemlani/Atmosphere/atmosphere.py
benchmarks/syllogistic/models/2012-Khemlani/Conversion/conversion.py
benchmarks/syllogistic/models/2012-Khemlani/Matching/matching.py
benchmarks/syllogistic/models/2012-Khemlani/MentalModels/mmt.py
benchmarks/syllogistic/models/2012-Khemlani/PHM/phm.py
benchmarks/syllogistic/models/2012-Khemlani/PSYCOP/psycop.py
benchmarks/syllogistic/models/2012-Khemlani/VerbalModels/verbalmodels.py
benchmarks/syllogistic/models/2019-Brand/TransSet/transset.py
benchmarks/syllogistic/models/2019-Riesterer/autoencoder/autoenc_model.py
benchmarks/syllogistic/models/2019-Riesterer/autoencoder/autoencoder.py
benchmarks/syllogistic/models/2019-Riesterer/mlp/onehot.py
benchmarks/syllogistic/models/2019-Riesterer/mlp/sylmlp.py
benchmarks/syllogistic/models/2019-Riesterer/rnn/onehot.py
benchmarks/syllogistic/models/2019-Riesterer/rnn/sylrnn.py
benchmarks/syllogistic/models/Baseline/MFA-Model/mfa_model.py
benchmarks/syllogistic/models/Baseline/NVC-Model/nvc_model.py
benchmarks/syllogistic/models/Baseline/Uniform-Model/uniform_model.py
ccobra/__init__.py
ccobra/comparator.py
ccobra/data.py
ccobra/encoder.py
ccobra/helper.py
ccobra/item.py
ccobra/model.py
ccobra/version.py
ccobra/benchmark/__init__.py
ccobra/benchmark/benchmark.py
ccobra/benchmark/contextmanager.py
ccobra/benchmark/evaluation_handler.py
ccobra/benchmark/evaluator.py
ccobra/benchmark/modelimporter.py
ccobra/benchmark/runner.py
ccobra/benchmark/comparators/__init__.py
ccobra/benchmark/comparators/absdiff.py
ccobra/benchmark/comparators/equality.py
ccobra/benchmark/comparators/nvc.py
ccobra/benchmark/comparators/squareddiff.py
ccobra/benchmark/visualization/__init__.py
ccobra/benchmark/visualization/html2canvas.min.js
ccobra-1.5.0.dist-info/licenses/LICENSE
ccobra-1.5.0.dist-info/METADATA
ccobra-1.5.0.dist-info/WHEEL
ccobra-1.5.0.dist-info/entry_points.txt
ccobra-1.5.0.dist-info/top_level.txt
ccobra-1.5.0.dist-info/RECORD
