Metadata-Version: 2.4
Name: ccobra
Version: 1.5.0
Summary: The CCOBRA framework.
Author-email: Nicolas Riesterer <riestern@tf.uni-freiburg.de>, Daniel Brand <daniel.brand@metech.tu-chemnitz.de>
License-Expression: MIT
Project-URL: Repository, https://github.com/CognitiveComputationLab/ccobra
Project-URL: Homepage, https://www.pva.tu-chemnitz.de/ccobra/
Classifier: Operating System :: OS Independent
Classifier: Programming Language :: Python :: 3
License-File: LICENSE
Dynamic: license-file
